fastmcp_agents/bridge/pydantic_ai/__init__.py
fastmcp_agents/bridge/pydantic_ai/logging.py
fastmcp_agents/bridge/pydantic_ai/toolset.py
fastmcp_agents_bridge_pydantic_ai-0.5.10.dist-info/WHEEL
fastmcp_agents_bridge_pydantic_ai-0.5.10.dist-info/METADATA
fastmcp_agents_bridge_pydantic_ai-0.5.10.dist-info/RECORD
