Metadata-Version: 2.3
Name: fastmcp-agents-bridge-pydantic-ai
Version: 0.5.10
Summary: Pydantic AI Agent Bridge
Requires-Dist: fastmcp
Requires-Dist: logfire>=3.25.0
Requires-Dist: pydantic-ai>=0.4.4
Requires-Python: >=3.13
